irontec/__init__.py
irontec/py.typed
irontec/livekit/__init__.py
irontec/livekit/plugins/__init__.py
irontec/livekit/plugins/piper/__init__.py
irontec/livekit/plugins/piper/tts.py
irontec/livekit/plugins/trebe/__init__.py
irontec/livekit/plugins/trebe/models.py
irontec/livekit/plugins/trebe/stt.py
irontec/livekit/plugins/trebe/tts.py
irontec_livekit_plugins-0.1.0.dist-info/licenses/LICENSE
irontec_livekit_plugins-0.1.0.dist-info/METADATA
irontec_livekit_plugins-0.1.0.dist-info/WHEEL
irontec_livekit_plugins-0.1.0.dist-info/top_level.txt
irontec_livekit_plugins-0.1.0.dist-info/RECORD
