Metadata-Version: 2.4
Name: irontec-livekit-plugins
Version: 0.1.0
Summary: Custom Livekit Agents plugins for STT and TTS services
Home-page: https://github.com/your-org/livekit-plugins
Author: Irontec S.L.
Author-email: "Irontec S.L." <communications@irontec.com>
License: Apache-2.0
Project-URL: Homepage, https://github.com/your-org/livekit-plugins
Project-URL: Repository, https://github.com/your-org/livekit-plugins
Project-URL: Documentation, https://github.com/your-org/livekit-plugins#readme
Project-URL: Bug Tracker, https://github.com/your-org/livekit-plugins/issues
Classifier: Development Status :: 3 - Alpha
Classifier: Intended Audience :: Developers
Classifier: License :: OSI Approved :: Apache Software License
Classifier: Operating System :: OS Independent
Classifier: Programming Language :: Python :: 3
Classifier: Programming Language :: Python :: 3.9
Classifier: Programming Language :: Python :: 3.10
Classifier: Programming Language :: Python :: 3.11
Classifier: Topic :: Multimedia :: Sound/Audio
Classifier: Topic :: Scientific/Engineering :: Artificial Intelligence
Classifier: Typing :: Typed
Requires-Python: >=3.9
License-File: LICENSE
Requires-Dist: livekit-agents
Requires-Dist: aiohttp
Requires-Dist: httpx
Requires-Dist: openai
Provides-Extra: dev
Requires-Dist: pytest; extra == "dev"
Requires-Dist: pytest-asyncio; extra == "dev"
Requires-Dist: black; extra == "dev"
Requires-Dist: flake8; extra == "dev"
Requires-Dist: mypy; extra == "dev"
Requires-Dist: types-aiohttp; extra == "dev"
Requires-Dist: types-httpx; extra == "dev"
Dynamic: author
Dynamic: home-page
Dynamic: license-file
Dynamic: requires-python
